{
  "foliennummer": 39,
  "überschrift": "Der Data Science Lifecycle",
  "canvas": {
    "width": 960.0,
    "height": 540.0,
    "unit": "pt"
  },
  "elemente": [
    {
      "typ": "bild",
      "datei": "pdf_page39_img1.jpeg",
      "z_index": 1,
      "position": [
        {
          "links": 555.510009765625,
          "oben": 167.14398193359375,
          "breite": 356.489990234375,
          "höhe": 326.57000732421875
        }
      ]
    },
    {
      "typ": "text",
      "inhalt": "Der Data Science Lifecycle",
      "paragraphs": [
        {
          "level": 0,
          "is_bullet": false,
          "textausrichtung": "left",
          "runs": [
            {
              "text": "Der Data Science Lifecycle",
              "schriftgröße": 35.040000915527344,
              "schriftart": "TimesNewRomanPS-BoldMT",
              "farbe": "#000000",
              "bold": true,
              "italic": false,
              "underline": null
            }
          ],
          "plain_text": "Der Data Science Lifecycle"
        }
      ],
      "z_index": 2,
      "position": {
        "links": 44.928001403808594,
        "oben": 73.10934448242188,
        "breite": 398.82532501220703,
        "höhe": 38.789283752441406
      }
    },
    {
      "typ": "text",
      "inhalt": "Data Science folgt einem strukturierten Prozess von\nProblemdefinition bis Deployment. Jede Phase beeinflusst Qualität\nund Nutzen der Ergebnisse.",
      "paragraphs": [
        {
          "level": 0,
          "is_bullet": false,
          "textausrichtung": "left",
          "runs": [
            {
              "text": "Data Science folgt einem strukturierten Prozess von ",
              "schriftgröße": 18.0,
              "schriftart": "TimesNewRomanPSMT",
              "farbe": "#000000",
              "bold": false,
              "italic": false,
              "underline": null
            }
          ],
          "plain_text": "Data Science folgt einem strukturierten Prozess von"
        },
        {
          "level": 0,
          "is_bullet": false,
          "textausrichtung": "left",
          "runs": [
            {
              "text": "Problemdefinition bis Deployment. Jede Phase beeinflusst Qualität ",
              "schriftgröße": 18.0,
              "schriftart": "TimesNewRomanPSMT",
              "farbe": "#000000",
              "bold": false,
              "italic": false,
              "underline": null
            }
          ],
          "plain_text": "Problemdefinition bis Deployment. Jede Phase beeinflusst Qualität"
        },
        {
          "level": 0,
          "is_bullet": false,
          "textausrichtung": "left",
          "runs": [
            {
              "text": "und Nutzen der Ergebnisse.",
              "schriftgröße": 18.0,
              "schriftart": "TimesNewRomanPSMT",
              "farbe": "#000000",
              "bold": false,
              "italic": false,
              "underline": null
            }
          ],
          "plain_text": "und Nutzen der Ergebnisse."
        }
      ],
      "z_index": 3,
      "position": {
        "links": 44.928001403808594,
        "oben": 172.14199829101562,
        "breite": 486.9881362915039,
        "höhe": 63.156005859375
      }
    },
    {
      "typ": "text",
      "inhalt": "• Definition klarer Geschäftsziele als Ausgangspunkt.",
      "paragraphs": [
        {
          "level": 0,
          "is_bullet": true,
          "textausrichtung": "left",
          "runs": [
            {
              "text": "•",
              "schriftgröße": 18.0,
              "schriftart": "ArialMT",
              "farbe": "#000000",
              "bold": false,
              "italic": false,
              "underline": null
            },
            {
              "text": " Definition klarer Geschäftsziele als Ausgangspunkt.",
              "schriftgröße": 18.0,
              "schriftart": "TimesNewRomanPSMT",
              "farbe": "#000000",
              "bold": false,
              "italic": false,
              "underline": null
            }
          ],
          "plain_text": "• Definition klarer Geschäftsziele als Ausgangspunkt."
        }
      ],
      "z_index": 4,
      "position": {
        "links": 44.928001403808594,
        "oben": 246.6800079345703,
        "breite": 392.3100357055664,
        "höhe": 20.177993774414062
      }
    },
    {
      "typ": "text",
      "inhalt": "• Datenaufbereitung nach dem Prinzip „Garbage in, Garbage",
      "paragraphs": [
        {
          "level": 0,
          "is_bullet": true,
          "textausrichtung": "left",
          "runs": [
            {
              "text": "•",
              "schriftgröße": 18.0,
              "schriftart": "ArialMT",
              "farbe": "#000000",
              "bold": false,
              "italic": false,
              "underline": null
            },
            {
              "text": " Datenaufbereitung nach dem Prinzip „",
              "schriftgröße": 18.0,
              "schriftart": "TimesNewRomanPSMT",
              "farbe": "#000000",
              "bold": false,
              "italic": false,
              "underline": null
            },
            {
              "text": "Garbage in, Garbage ",
              "schriftgröße": 18.0,
              "schriftart": "TimesNewRomanPSMT",
              "farbe": "#50164A",
              "bold": false,
              "italic": false,
              "underline": null
            }
          ],
          "plain_text": "• Datenaufbereitung nach dem Prinzip „Garbage in, Garbage"
        }
      ],
      "z_index": 5,
      "position": {
        "links": 44.928001403808594,
        "oben": 278.3599853515625,
        "breite": 449.15198516845703,
        "höhe": 20.178009033203125
      }
    },
    {
      "typ": "text",
      "inhalt": "out“.",
      "paragraphs": [
        {
          "level": 0,
          "is_bullet": false,
          "textausrichtung": "left",
          "runs": [
            {
              "text": "out",
              "schriftgröße": 18.0,
              "schriftart": "TimesNewRomanPSMT",
              "farbe": "#50164A",
              "bold": false,
              "italic": false,
              "underline": null
            },
            {
              "text": "“.",
              "schriftgröße": 18.0,
              "schriftart": "TimesNewRomanPSMT",
              "farbe": "#000000",
              "bold": false,
              "italic": false,
              "underline": null
            }
          ],
          "plain_text": "out“."
        }
      ],
      "z_index": 6,
      "position": {
        "links": 62.928001403808594,
        "oben": 300.2120056152344,
        "breite": 35.459999084472656,
        "höhe": 19.925994873046875
      }
    },
    {
      "typ": "text",
      "inhalt": "• Modelltraining und kontinuierliche Evaluation helfen dabei, die",
      "paragraphs": [
        {
          "level": 0,
          "is_bullet": true,
          "textausrichtung": "left",
          "runs": [
            {
              "text": "•",
              "schriftgröße": 18.0,
              "schriftart": "ArialMT",
              "farbe": "#000000",
              "bold": false,
              "italic": false,
              "underline": null
            },
            {
              "text": " Modelltraining und kontinuierliche Evaluation helfen dabei, die ",
              "schriftgröße": 18.0,
              "schriftart": "TimesNewRomanPSMT",
              "farbe": "#000000",
              "bold": false,
              "italic": false,
              "underline": null
            }
          ],
          "plain_text": "• Modelltraining und kontinuierliche Evaluation helfen dabei, die"
        }
      ],
      "z_index": 7,
      "position": {
        "links": 44.928001403808594,
        "oben": 331.5400085449219,
        "breite": 481.7879409790039,
        "höhe": 20.178009033203125
      }
    },
    {
      "typ": "text",
      "inhalt": "Leistungsfähigkeit der Modelle zu überprüfen und bei Bedarf\nanzupassen.",
      "paragraphs": [
        {
          "level": 0,
          "is_bullet": false,
          "textausrichtung": "left",
          "runs": [
            {
              "text": "Leistungsfähigkeit der Modelle zu überprüfen und bei Bedarf ",
              "schriftgröße": 18.0,
              "schriftart": "TimesNewRomanPSMT",
              "farbe": "#000000",
              "bold": false,
              "italic": false,
              "underline": null
            }
          ],
          "plain_text": "Leistungsfähigkeit der Modelle zu überprüfen und bei Bedarf"
        },
        {
          "level": 0,
          "is_bullet": false,
          "textausrichtung": "left",
          "runs": [
            {
              "text": "anzupassen.",
              "schriftgröße": 18.0,
              "schriftart": "TimesNewRomanPSMT",
              "farbe": "#000000",
              "bold": false,
              "italic": false,
              "underline": null
            }
          ],
          "plain_text": "anzupassen."
        }
      ],
      "z_index": 8,
      "position": {
        "links": 62.928001403808594,
        "oben": 353.3919982910156,
        "breite": 446.9219741821289,
        "höhe": 41.5260009765625
      }
    },
    {
      "typ": "text",
      "inhalt": "• Deployment und Monitoring im produktiven Umfeld stellen",
      "paragraphs": [
        {
          "level": 0,
          "is_bullet": true,
          "textausrichtung": "left",
          "runs": [
            {
              "text": "•",
              "schriftgröße": 18.0,
              "schriftart": "ArialMT",
              "farbe": "#000000",
              "bold": false,
              "italic": false,
              "underline": null
            },
            {
              "text": " Deployment und Monitoring im produktiven Umfeld stellen ",
              "schriftgröße": 18.0,
              "schriftart": "TimesNewRomanPSMT",
              "farbe": "#000000",
              "bold": false,
              "italic": false,
              "underline": null
            }
          ],
          "plain_text": "• Deployment und Monitoring im produktiven Umfeld stellen"
        }
      ],
      "z_index": 9,
      "position": {
        "links": 44.928001403808594,
        "oben": 406.29998779296875,
        "breite": 455.56995391845703,
        "höhe": 20.178009033203125
      }
    },
    {
      "typ": "text",
      "inhalt": "sicher, dass Modelle langfristig zuverlässig funktionieren und\nkontinuierlich verbessert werden können.",
      "paragraphs": [
        {
          "level": 0,
          "is_bullet": false,
          "textausrichtung": "left",
          "runs": [
            {
              "text": "sicher, dass Modelle langfristig zuverlässig funktionieren und ",
              "schriftgröße": 18.0,
              "schriftart": "TimesNewRomanPSMT",
              "farbe": "#000000",
              "bold": false,
              "italic": false,
              "underline": null
            }
          ],
          "plain_text": "sicher, dass Modelle langfristig zuverlässig funktionieren und"
        },
        {
          "level": 0,
          "is_bullet": false,
          "textausrichtung": "left",
          "runs": [
            {
              "text": "kontinuierlich verbessert werden können.",
              "schriftgröße": 18.0,
              "schriftart": "TimesNewRomanPSMT",
              "farbe": "#000000",
              "bold": false,
              "italic": false,
              "underline": null
            }
          ],
          "plain_text": "kontinuierlich verbessert werden können."
        }
      ],
      "z_index": 10,
      "position": {
        "links": 62.928001403808594,
        "oben": 428.1780090332031,
        "breite": 448.0559768676758,
        "höhe": 41.5260009765625
      }
    }
  ],
  "semantik": {
    "segmentierung": {
      "abschnitte": [
        "Der Data Science Lifecycle\nDer Data Science Lifecycle\nData Science folgt einem strukturierten Prozess von\nProblemdefinition bis Deployment. Jede Phase beeinflusst Qualität\nund Nutzen der Ergebnisse.\n• Definition klarer Geschäftsziele als Ausgangspunkt.\n• Datenaufbereitung nach dem Prinzip „Garbage in, Garbage\nout“.\n• Modelltraining und kontinuierliche Evaluation helfen dabei, die\nLeistungsfähigkeit der Modelle zu überprüfen und bei Bedarf\nanzupassen.\n• Deployment und Monitoring im produktiven Umfeld stellen\nsicher, dass Modelle langfristig zuverlässig funktionieren und\nkontinuierlich verbessert werden können."
      ],
      "saetze": [
        "Der Data Science Lifecycle",
        "Der Data Science Lifecycle",
        "Data Science folgt einem strukturierten Prozess von",
        "Problemdefinition bis Deployment.",
        "Jede Phase beeinflusst Qualität",
        "und Nutzen der Ergebnisse.",
        "Definition klarer Geschäftsziele als Ausgangspunkt.",
        "Datenaufbereitung nach dem Prinzip „Garbage in, Garbage",
        "out“.",
        "Modelltraining und kontinuierliche Evaluation helfen dabei, die",
        "Leistungsfähigkeit der Modelle zu überprüfen und bei Bedarf",
        "anzupassen.",
        "Deployment und Monitoring im produktiven Umfeld stellen",
        "sicher, dass Modelle langfristig zuverlässig funktionieren und",
        "kontinuierlich verbessert werden können."
      ]
    },
    "textkomplexitaet": {
      "wortanzahl": 73,
      "satzanzahl": 15,
      "durchschnitt_wortlaenge": 7.192,
      "durchschnitt_satzlaenge_woerter": 4.867,
      "type_token_ratio": 0.795
    },
    "keywords": [
      "lifecycle data",
      "science lifecycle",
      "lifecycle",
      "data science",
      "modelle langfristig",
      "prozess problemdefinition",
      "strukturierten prozess",
      "datenaufbereitung nach",
      "datenaufbereitung",
      "ausgangspunkt datenaufbereitung"
    ],
    "embeddings": {
      "ueberschrift": [
        -0.3262536823749542,
        0.2710980772972107,
        -0.41197657585144043,
        -0.2780110836029053,
        -0.010089578106999397,
        -0.25947123765945435,
        -0.2684580981731415,
        0.021365975961089134,
        -0.06761884689331055,
        0.28111475706100464,
        0.18697500228881836,
        -0.19915255904197693,
        0.38038474321365356,
        -0.21644021570682526,
        -0.3507194221019745,
        -0.04999076575040817,
        -0.18739068508148193,
        -0.43238091468811035,
        -0.21620707213878632,
        -0.21587465703487396,
        -0.004788284655660391,
        -0.25282803177833557,
        -0.13453704118728638,
        -0.24872028827667236,
        -0.07522042840719223,
        0.12967002391815186,
        -0.3765646815299988,
        -0.022649165242910385,
        -0.11912810802459717,
        -0.23181040585041046,
        0.35196632146835327,
        0.38346266746520996,
        0.27416616678237915,
        -0.1942116916179657,
        -0.021316135302186012,
        0.0024813711643218994,
        0.06500046700239182,
        -0.1755402833223343,
        -0.31076496839523315,
        0.285340815782547,
        -0.10683339834213257,
        0.0457640066742897,
        -0.015057169832289219,
        0.09828246384859085,
        0.008522055111825466,
        -0.16375942528247833,
        -0.037090398371219635,
        -0.6235051155090332,
        -0.2581571638584137,
        -0.010569329373538494,
        -0.6249688267707825,
        -0.35440659523010254,
        -0.04176268354058266,
        -0.12809374928474426,
        -0.07740499824285507,
        0.05935152247548103,
        0.10085863620042801,
        -0.05165529251098633,
        -0.20550788938999176,
        -0.3609810471534729,
        0.2176782339811325,
        -0.17093685269355774,
        -0.2166639119386673,
        0.10591541230678558,
        0.23326893150806427,
        0.21300847828388214,
        0.09246418625116348,
        -0.12314479798078537,
        0.30495116114616394,
        -0.3296082317829132,
        -0.34799689054489136,
        0.18049955368041992,
        -0.5657674074172974,
        -0.048339810222387314,
        -0.2811024785041809,
        0.33595162630081177,
        0.06227295473217964,
        -0.05672513693571091,
        0.3885498642921448,
        -0.3823544979095459,
        -0.0016312679508700967,
        -0.2173585593700409,
        -0.19704341888427734,
        -0.19869542121887207,
        -0.07940329611301422,
        -0.1067800521850586,
        0.04110909625887871,
        -0.16683681309223175,
        -0.11482123285531998,
        0.06706644594669342,
        0.3817785680294037,
        0.21522743999958038,
        -0.06271376460790634,
        -0.22604453563690186,
        -0.3129311203956604,
        0.3916221261024475,
        -0.12903793156147003,
        0.12401510775089264,
        0.7248657941818237,
        0.6904283165931702,
        -0.19727429747581482,
        0.0884891077876091,
        -0.4307343661785126,
        0.18811193108558655,
        0.15497151017189026,
        -0.20901718735694885,
        -0.1489541232585907,
        -0.046610407531261444,
        0.14768095314502716,
        0.0853404775261879,
        0.3895384967327118,
        0.19011877477169037,
        -0.006752580404281616,
        0.0445835217833519,
        0.1940268576145172,
        -0.07501745223999023,
        -0.314771443605423,
        0.1782323569059372,
        0.12781845033168793,
        0.4946552813053131,
        0.1375398337841034,
        0.08851953595876694,
        0.0426110103726387,
        0.0958448275923729,
        0.4914246201515198,
        -0.25930166244506836,
        -0.038419026881456375,
        0.20860670506954193,
        0.13164401054382324,
        -0.30841436982154846,
        0.5597113966941833,
        -0.0026554991491138935,
        -0.24992923438549042,
        0.13730962574481964,
        -0.19309303164482117,
        -0.16592657566070557,
        0.42577147483825684,
        -0.025939060375094414,
        -0.03263368085026741,
        0.5515114068984985,
        -0.009558136574923992,
        0.10866010934114456,
        0.2515745759010315,
        0.10638083517551422,
        -0.3160376250743866,
        0.30162400007247925,
        0.16257891058921814,
        -0.37507233023643494,
        -0.015536482445895672,
        -0.17718133330345154,
        0.4000619351863861,
        -0.3208574652671814,
        0.2536563277244568,
        0.06345132738351822,
        0.05944357439875603,
        -0.01653384417295456,
        0.07207246124744415,
        0.04060983657836914,
        -0.09250693768262863,
        0.0348546989262104,
        -0.19785751402378082,
        0.4478232264518738,
        0.05437252297997475,
        0.022479768842458725,
        -0.004948087967932224,
        -0.06061745062470436,
        0.18173357844352722,
        0.1851920187473297,
        0.13653340935707092,
        0.374082088470459,
        0.5608294606208801,
        -0.17738746106624603,
        -0.3030913770198822,
        -0.35576313734054565,
        0.46870893239974976,
        0.32668831944465637,
        -0.146902933716774,
        -0.04871944338083267,
        0.33982327580451965,
        -0.1525125950574875,
        0.1957792043685913,
        -0.11229275912046432,
        0.07736320793628693,
        0.13778874278068542,
        -0.1277872771024704,
        -0.3937711715698242,
        -0.06331230700016022,
        0.13195063173770905,
        -0.13327744603157043,
        0.17814254760742188,
        0.3383294939994812,
        0.3716876208782196,
        0.5126606822013855,
        0.2613273561000824,
        -0.03988420218229294,
        -0.3329073488712311,
        0.5388015508651733,
        0.10910572111606598,
        0.18046392500400543,
        -0.5012219548225403,
        -0.08398396521806717,
        -0.275860458612442,
        -0.06982385367155075,
        -0.04320487752556801,
        0.08599621802568436,
        -0.27640998363494873,
        -0.2166016846895218,
        0.31419840455055237,
        0.058832671493291855,
        -0.11798684298992157,
        -0.494215726852417,
        -0.3045925199985504,
        -0.20615828037261963,
        0.12301994860172272,
        -0.10052107274532318,
        -0.32602787017822266,
        -0.3097071349620819,
        0.17836426198482513,
        0.14418897032737732,
        0.03347984701395035,
        0.2300325185060501,
        -0.2236076146364212,
        0.05115634202957153,
        -0.36395469307899475,
        -0.16568811237812042,
        0.2249838411808014,
        -0.30377551913261414,
        0.04712459072470665,
        0.22014859318733215,
        -0.03848423436284065,
        -0.1879824697971344,
        0.19851601123809814,
        0.33128008246421814,
        0.18876466155052185,
        -0.17959043383598328,
        -0.06882376968860626,
        0.11300832778215408,
        -0.029742302373051643,
        -0.1366194486618042,
        -0.4677892327308655,
        0.3146977126598358,
        -0.35467857122421265,
        -0.027711601927876472,
        -0.11917202174663544,
        -0.4408731758594513,
        0.06613707542419434,
        -0.8187479376792908,
        -0.0013574808835983276,
        0.3125286102294922,
        0.2777582108974457,
        -0.48129209876060486,
        -0.36370131373405457,
        0.16628359258174896,
        -0.2941785752773285,
        -0.26118358969688416,
        -0.18976221978664398,
        0.14147843420505524,
        0.05268576741218567,
        0.2426423281431198,
        -0.004527647979557514,
        0.5343230962753296,
        -0.46280527114868164,
        0.27598482370376587,
        0.1362786591053009,
        -0.03534391149878502,
        0.1969924420118332,
        -0.28497496247291565,
        -0.1498064249753952,
        0.2912558615207672,
        -0.0052024610340595245,
        -0.3211000859737396,
        0.2255900651216507,
        -0.07784001529216766,
        0.2756849527359009,
        0.22451095283031464,
        -0.019131895154714584,
        0.14513151347637177,
        -0.37540993094444275,
        0.24938616156578064,
        0.21133048832416534,
        -0.14028118550777435,
        0.04322708398103714,
        -0.10746345669031143,
        0.05595003813505173,
        0.09156595170497894,
        0.05176865682005882,
        0.12395378202199936,
        0.10987218469381332,
        -0.4387405812740326,
        0.38722944259643555,
        0.14185288548469543,
        -0.01251849066466093,
        -0.5553052425384521,
        0.08082585781812668,
        0.17979001998901367,
        -0.20799484848976135,
        -0.25974801182746887,
        -0.3006869852542877,
        -0.07532422244548798,
        -0.014050445519387722,
        -0.5503907203674316,
        0.08573821932077408,
        0.29806405305862427,
        0.23062822222709656,
        -0.287643700838089,
        -0.17597432434558868,
        0.48192405700683594,
        0.19130182266235352,
        0.12953242659568787,
        0.003046077210456133,
        -0.12308907508850098,
        -0.5026608109474182,
        0.3185269832611084,
        -0.14511744678020477,
        -0.1632591336965561,
        -0.22191931307315826,
        -0.5117300748825073,
        0.5610753297805786,
        0.10838143527507782,
        -0.3283555805683136,
        -0.009196801111102104,
        0.13914823532104492,
        0.24617180228233337,
        0.4592835605144501,
        0.41462603211402893,
        0.2718007564544678,
        0.19626733660697937,
        -0.09839843213558197,
        0.3607846200466156,
        0.022271981462836266,
        0.44606781005859375,
        0.06602277606725693,
        -0.10750149190425873,
        0.16010186076164246,
        0.16191409528255463,
        0.07125850021839142,
        -0.029391979798674583,
        -0.04124594107270241,
        -0.33168673515319824,
        0.0903002992272377,
        0.4213685989379883,
        0.2942742705345154,
        -0.062891386449337,
        -0.04426601901650429,
        -0.02130095474421978,
        -0.004224847536534071,
        0.5260399580001831,
        0.3815680146217346,
        -0.02583417482674122,
        -0.3213537335395813,
        -0.012882208451628685,
        -0.09966109693050385,
        0.004561803303658962,
        -0.06800113618373871,
        0.0677802637219429,
        -0.24767644703388214,
        0.14774520695209503,
        0.5693480968475342,
        -0.18594679236412048,
        0.08368168026208878,
        -0.07974217087030411,
        0.3620774447917938,
        -0.18511971831321716,
        0.4084133505821228,
        -0.05961442366242409,
        0.021185964345932007,
        -0.24839921295642853,
        0.10359003394842148,
        0.21006135642528534,
        0.040821101516485214,
        -0.23463423550128937,
        0.04216933622956276,
        0.1828812211751938,
        -0.01385329756885767,
        0.11052677780389786,
        0.4189775586128235,
        0.25008854269981384,
        0.2395457923412323,
        -0.15393796563148499,
        0.027100691571831703,
        -0.03342074528336525,
        -0.1977565586566925,
        0.0371226891875267,
        -0.350780725479126
      ],
      "fliesstext": [
        -0.09560937434434891,
        0.20502957701683044,
        -0.0952124297618866,
        -0.2062671184539795,
        0.05614732578396797,
        -0.17101120948791504,
        -0.07645584642887115,
        0.002497454173862934,
        -0.11135473102331161,
        0.12886138260364532,
        0.04750649258494377,
        0.11966833472251892,
        0.27037444710731506,
        -0.10557091981172562,
        -0.15765197575092316,
        -0.143966406583786,
        0.06662248075008392,
        -0.2818094789981842,
        -0.049466341733932495,
        -0.04399242252111435,
        -0.05648336932063103,
        -0.12267760187387466,
        0.12156585603952408,
        -0.012022251263260841,
        -0.201068714261055,
        0.2027732878923416,
        -0.059164099395275116,
        -0.09954927861690521,
        0.011543420143425465,
        -0.12423509359359741,
        0.12529979646205902,
        0.24700231850147247,
        -0.0068685635924339294,
        -0.22359149158000946,
        -0.050956737250089645,
        0.014337991364300251,
        0.03806888312101364,
        -0.11504855751991272,
        -0.20096859335899353,
        0.1374894082546234,
        -0.08546072989702225,
        -0.006443972233682871,
        0.1086622029542923,
        -0.07360328733921051,
        0.008834308944642544,
        -0.20282235741615295,
        -0.016774741932749748,
        -0.34361857175827026,
        -0.28237277269363403,
        -0.11195269227027893,
        -0.3148300051689148,
        -0.2733181416988373,
        0.04789165034890175,
        -0.20454257726669312,
        0.0324484221637249,
        0.1354576051235199,
        0.17531907558441162,
        -0.013139002025127411,
        -0.3097619116306305,
        -0.1764584183692932,
        0.12677057087421417,
        -0.1995365172624588,
        0.021867036819458008,
        0.037537090480327606,
        0.22549717128276825,
        0.19546976685523987,
        0.1000571995973587,
        0.11176460981369019,
        0.18531019985675812,
        -0.06381463259458542,
        -0.29213252663612366,
        0.10520564019680023,
        -0.2178432196378708,
        -0.02434178628027439,
        -0.17004011571407318,
        0.18867044150829315,
        0.019845031201839447,
        -0.12593074142932892,
        0.19721342623233795,
        -0.37098923325538635,
        0.004136133473366499,
        -0.11499612778425217,
        -0.0984828770160675,
        -0.06312929093837738,
        -0.05917464941740036,
        -0.10316616296768188,
        -0.023650750517845154,
        -0.13013507425785065,
        -0.00028309025219641626,
        0.10556439310312271,
        0.2568452060222626,
        0.09349992126226425,
        0.02158348076045513,
        -0.15369069576263428,
        -0.2286827713251114,
        0.21345913410186768,
        -0.16203175485134125,
        0.0586368702352047,
        0.16190987825393677,
        0.3513210415840149,
        -0.12167081236839294,
        0.05174160376191139,
        -0.2853794991970062,
        0.05050872266292572,
        0.17338941991329193,
        0.038167934864759445,
        -0.1675977259874344,
        -0.09139910340309143,
        0.01632491871714592,
        0.11153558641672134,
        0.15116918087005615,
        0.1808769851922989,
        0.005669566337019205,
        -0.04928704723715782,
        0.0037941455375403166,
        0.15025067329406738,
        -0.13914906978607178,
        0.14748866856098175,
        -0.013428033329546452,
        0.2065589427947998,
        0.1498371660709381,
        -0.10355270653963089,
        0.11997576802968979,
        0.030313055962324142,
        0.3128301799297333,
        -0.12095200270414352,
        -0.0973152220249176,
        -0.1675911247730255,
        -0.0767609253525734,
        -0.22781510651111603,
        0.40317946672439575,
        -0.0015202380018308759,
        -0.15739291906356812,
        0.0976264476776123,
        -0.16909317672252655,
        -0.08258222043514252,
        0.23912020027637482,
        -0.026370970532298088,
        0.07869638502597809,
        0.28947240114212036,
        -4.940298367728246e-06,
        0.06315682083368301,
        0.3458428680896759,
        -0.037783920764923096,
        -0.24490725994110107,
        0.2447616457939148,
        0.05196776241064072,
        -0.1843651384115219,
        0.060851115733385086,
        -0.12931764125823975,
        0.24247537553310394,
        -0.07397180795669556,
        0.22986944019794464,
        0.04077192768454552,
        0.016690757125616074,
        0.04054206982254982,
        -0.12993033230304718,
        -0.15220163762569427,
        -0.027576789259910583,
        -0.0049803308211266994,
        -0.1476021558046341,
        0.2906009256839752,
        0.04542441666126251,
        -0.13719727098941803,
        -0.30354011058807373,
        0.09784848242998123,
        0.13702712953090668,
        -0.16656449437141418,
        0.13390660285949707,
        0.07613403350114822,
        0.329403817653656,
        -0.013283410109579563,
        -0.15583142638206482,
        -0.3116299510002136,
        0.10388454794883728,
        0.27025097608566284,
        -0.016123663634061813,
        -0.0728176012635231,
        0.17239145934581757,
        -0.17577141523361206,
        0.37297070026397705,
        -0.12711326777935028,
        0.02308882772922516,
        -0.013462868519127369,
        0.013971798121929169,
        -0.1615585833787918,
        -0.054496895521879196,
        0.004029344767332077,
        -0.05377526953816414,
        0.09609764069318771,
        0.051409341394901276,
        0.176055446267128,
        0.39619696140289307,
        0.18260200321674347,
        -0.059839773923158646,
        -0.16729187965393066,
        0.3673592209815979,
        0.018117500469088554,
        0.11522603780031204,
        -0.19885070621967316,
        -0.11478278040885925,
        -0.03440551459789276,
        -0.05267015099525452,
        -0.04273509234189987,
        -0.0486936941742897,
        -0.12657028436660767,
        -0.018990924581885338,
        0.051818933337926865,
        0.08326928317546844,
        -0.09909375011920929,
        -0.42392703890800476,
        -0.10333046317100525,
        -0.1908363550901413,
        0.07255381345748901,
        -0.004662883467972279,
        -0.1636914163827896,
        -0.035295430570840836,
        0.15329843759536743,
        0.09569669514894485,
        0.02283814363181591,
        0.1625361293554306,
        0.12439113855361938,
        0.0878201574087143,
        -0.1887062042951584,
        0.019699281081557274,
        0.2079685926437378,
        -0.11652124673128128,
        -0.017051029950380325,
        0.17018340528011322,
        -0.11542115360498428,
        -0.1470731645822525,
        -0.08345359563827515,
        0.13370025157928467,
        0.11200481653213501,
        -0.20963111519813538,
        -0.014376185834407806,
        -0.0574854239821434,
        0.06701642274856567,
        -0.14004431664943695,
        -0.21684297919273376,
        0.13181614875793457,
        -0.16818612813949585,
        0.05602497607469559,
        -0.11585099250078201,
        -0.21516969799995422,
        -0.04633361101150513,
        -0.46122580766677856,
        -0.04421323910355568,
        0.1837235391139984,
        0.11584640294313431,
        -0.24503137171268463,
        -0.1862068772315979,
        0.06966704875230789,
        -0.18889300525188446,
        -0.17302483320236206,
        -0.1892806589603424,
        0.049503885209560394,
        0.005294515285640955,
        0.10253394395112991,
        0.036456555128097534,
        0.27471867203712463,
        -0.20650307834148407,
        0.23718897998332977,
        0.2060568630695343,
        -0.08969007432460785,
        -0.03199625387787819,
        -0.3075917363166809,
        -0.01639709062874317,
        0.018491700291633606,
        0.10783310979604721,
        -0.12366640567779541,
        0.06319928169250488,
        -0.13341210782527924,
        0.17931441962718964,
        0.14159750938415527,
        0.039569955319166183,
        0.05745260789990425,
        -0.21165820956230164,
        0.1677722930908203,
        0.13937969505786896,
        0.022181479260325432,
        -0.048640090972185135,
        -0.1099282056093216,
        0.10725342482328415,
        -0.017037443816661835,
        0.04845886304974556,
        0.1696922928094864,
        -0.034721069037914276,
        -0.10997814685106277,
        0.11296596378087997,
        0.06300617009401321,
        -0.011987358331680298,
        -0.2273234874010086,
        -0.11851231753826141,
        0.06893537938594818,
        -0.05294579267501831,
        -0.11755616217851639,
        -0.14655111730098724,
        -0.057182006537914276,
        -0.08398661762475967,
        -0.27409613132476807,
        -0.08093058317899704,
        0.02964956685900688,
        0.031911976635456085,
        -0.1381441354751587,
        -0.2221112996339798,
        0.25826776027679443,
        0.03272976353764534,
        -0.11085908114910126,
        0.03091558627784252,
        -0.06938732415437698,
        -0.29192474484443665,
        0.23333649337291718,
        -0.05417277291417122,
        -0.11026863008737564,
        -0.16236452758312225,
        -0.23412659764289856,
        0.3547685742378235,
        0.059658199548721313,
        -0.15185418725013733,
        -0.016398129984736443,
        0.06827706098556519,
        0.2868726849555969,
        0.1486637443304062,
        0.25375208258628845,
        -0.00960975419729948,
        0.05446285754442215,
        0.06186578795313835,
        0.19823144376277924,
        0.004074069205671549,
        0.22350573539733887,
        0.04193129763007164,
        -0.031348817050457,
        0.058353740721940994,
        -0.029437357559800148,
        0.13268457353115082,
        -0.06843443959951401,
        0.20800553262233734,
        -0.2043101191520691,
        0.030747486278414726,
        0.30775952339172363,
        0.013780731707811356,
        -0.34591734409332275,
        0.033002786338329315,
        -0.027900174260139465,
        0.04436492174863815,
        0.3377499580383301,
        0.3281783163547516,
        -0.05580638721585274,
        -0.23415377736091614,
        0.0392296276986599,
        0.10560893267393112,
        0.05847612023353577,
        0.009215102531015873,
        0.07777615636587143,
        -0.20125967264175415,
        0.07554548233747482,
        0.32944929599761963,
        0.019079148769378662,
        0.13358379900455475,
        -0.04807279631495476,
        0.33050185441970825,
        -0.10788015276193619,
        0.14962562918663025,
        -0.01901758462190628,
        -0.06243952736258507,
        -0.10396149754524231,
        0.0926210805773735,
        0.046887755393981934,
        -0.052265703678131104,
        -0.10526790469884872,
        0.026093890890479088,
        0.07664494216442108,
        -0.006629984360188246,
        0.14286062121391296,
        0.3132576048374176,
        0.1725117266178131,
        0.19226928055286407,
        0.11269711703062057,
        0.15383033454418182,
        -0.06563334912061691,
        0.06115526333451271,
        0.15488821268081665,
        -0.12537311017513275
      ]
    },
    "cosine": {
      "ueberschrift_vs_fliesstext": 0.833932
    },
    "language_mode": "mixed",
    "zusammenfassung": {
      "modus": "t5",
      "wortanzahl": 73,
      "kurzer_originaltext": "",
      "summary": "Der Data Science Lifecycle Data Science folgt einem strukturierten Prozess von Problemdefinition bis Deployment. Jede Phase beeinflusst Qualität und Nutzen der Ergebnisse.",
      "modell": "t5-small"
    },
    "pfade": {
      "json_datei": "data\\processed\\pdf_slide_039.json",
      "assets_verzeichnis": "export\\assets"
    }
  }
}