{
  "foliennummer": 36,
  "überschrift": "Implementierungsstrategie",
  "canvas": {
    "width": 960.0,
    "height": 540.0,
    "unit": "pt"
  },
  "elemente": [
    {
      "typ": "text",
      "inhalt": "Implementierungsstrategie",
      "paragraphs": [
        {
          "level": 0,
          "is_bullet": false,
          "textausrichtung": "left",
          "runs": [
            {
              "text": "Implementierungsstrategie",
              "schriftgröße": 35.040000915527344,
              "schriftart": "TimesNewRomanPS-BoldMT",
              "farbe": "#000000",
              "bold": true,
              "italic": false,
              "underline": null
            }
          ],
          "plain_text": "Implementierungsstrategie"
        }
      ],
      "z_index": 1,
      "position": {
        "links": 44.06399917602539,
        "oben": 73.10934448242188,
        "breite": 402.78478622436523,
        "höhe": 38.789283752441406
      }
    },
    {
      "typ": "text",
      "inhalt": "Die erfolgreiche Einführung von Big Data erfordert strukturierte Planung und agile Umsetzung. Technologische\nIntegration muss mit Geschäftsprozessen harmonieren.",
      "paragraphs": [
        {
          "level": 0,
          "is_bullet": false,
          "textausrichtung": "center",
          "runs": [
            {
              "text": "Die erfolgreiche Einführung von Big Data erfordert strukturierte Planung und agile Umsetzung. Technologische ",
              "schriftgröße": 18.0,
              "schriftart": "TimesNewRomanPSMT",
              "farbe": "#000000",
              "bold": false,
              "italic": false,
              "underline": null
            }
          ],
          "plain_text": "Die erfolgreiche Einführung von Big Data erfordert strukturierte Planung und agile Umsetzung. Technologische"
        },
        {
          "level": 0,
          "is_bullet": false,
          "textausrichtung": "center",
          "runs": [
            {
              "text": "Integration muss mit Geschäftsprozessen harmonieren.",
              "schriftgröße": 18.0,
              "schriftart": "TimesNewRomanPSMT",
              "farbe": "#000000",
              "bold": false,
              "italic": false,
              "underline": null
            }
          ],
          "plain_text": "Integration muss mit Geschäftsprozessen harmonieren."
        }
      ],
      "z_index": 2,
      "position": {
        "links": 44.06399917602539,
        "oben": 181.58200073242188,
        "breite": 811.4042625427246,
        "höhe": 41.5260009765625
      }
    },
    {
      "typ": "text",
      "inhalt": "• Klare Zieldefinition vor Projektstart hilft Unternehmen dabei, den Nutzen von Datenprojekten messbar zu",
      "paragraphs": [
        {
          "level": 0,
          "is_bullet": true,
          "textausrichtung": "center",
          "runs": [
            {
              "text": "•",
              "schriftgröße": 18.0,
              "schriftart": "ArialMT",
              "farbe": "#000000",
              "bold": false,
              "italic": false,
              "underline": null
            },
            {
              "text": " Klare Zieldefinition vor Projektstart hilft Unternehmen dabei, den Nutzen von Datenprojekten messbar zu ",
              "schriftgröße": 18.0,
              "schriftart": "TimesNewRomanPSMT",
              "farbe": "#000000",
              "bold": false,
              "italic": false,
              "underline": null
            }
          ],
          "plain_text": "• Klare Zieldefinition vor Projektstart hilft Unternehmen dabei, den Nutzen von Datenprojekten messbar zu"
        }
      ],
      "z_index": 3,
      "position": {
        "links": 44.06399917602539,
        "oben": 234.50999450683594,
        "breite": 785.7002220153809,
        "höhe": 20.177993774414062
      }
    },
    {
      "typ": "text",
      "inhalt": "machen und Prioritäten festzulegen.",
      "paragraphs": [
        {
          "level": 0,
          "is_bullet": false,
          "textausrichtung": "left",
          "runs": [
            {
              "text": "machen und Prioritäten festzulegen.",
              "schriftgröße": 18.0,
              "schriftart": "TimesNewRomanPSMT",
              "farbe": "#000000",
              "bold": false,
              "italic": false,
              "underline": null
            }
          ],
          "plain_text": "machen und Prioritäten festzulegen."
        }
      ],
      "z_index": 4,
      "position": {
        "links": 62.06399917602539,
        "oben": 256.36199951171875,
        "breite": 259.1100425720215,
        "höhe": 19.925994873046875
      }
    },
    {
      "typ": "text",
      "inhalt": "• Auswahl geeigneter Technologien und Partner ist entscheidend, um leistungsfähige Analyseplattformen und",
      "paragraphs": [
        {
          "level": 0,
          "is_bullet": true,
          "textausrichtung": "center",
          "runs": [
            {
              "text": "•",
              "schriftgröße": 18.0,
              "schriftart": "ArialMT",
              "farbe": "#000000",
              "bold": false,
              "italic": false,
              "underline": null
            },
            {
              "text": " Auswahl geeigneter Technologien und Partner ist entscheidend, um leistungsfähige Analyseplattformen und ",
              "schriftgröße": 18.0,
              "schriftart": "TimesNewRomanPSMT",
              "farbe": "#000000",
              "bold": false,
              "italic": false,
              "underline": null
            }
          ],
          "plain_text": "• Auswahl geeigneter Technologien und Partner ist entscheidend, um leistungsfähige Analyseplattformen und"
        }
      ],
      "z_index": 5,
      "position": {
        "links": 44.06399917602539,
        "oben": 287.7900085449219,
        "breite": 799.0745506286621,
        "höhe": 20.178009033203125
      }
    },
    {
      "typ": "text",
      "inhalt": "eine stabile Dateninfrastruktur aufzubauen.",
      "paragraphs": [
        {
          "level": 0,
          "is_bullet": false,
          "textausrichtung": "left",
          "runs": [
            {
              "text": "eine stabile Dateninfrastruktur aufzubauen.",
              "schriftgröße": 18.0,
              "schriftart": "TimesNewRomanPSMT",
              "farbe": "#000000",
              "bold": false,
              "italic": false,
              "underline": null
            }
          ],
          "plain_text": "eine stabile Dateninfrastruktur aufzubauen."
        }
      ],
      "z_index": 6,
      "position": {
        "links": 62.06399917602539,
        "oben": 309.6419982910156,
        "breite": 311.0400047302246,
        "höhe": 19.925994873046875
      }
    },
    {
      "typ": "text",
      "inhalt": "• Nutzung agiler Projektmanagementmethoden ermöglicht eine flexible Entwicklung und schnelle Anpassung an",
      "paragraphs": [
        {
          "level": 0,
          "is_bullet": true,
          "textausrichtung": "center",
          "runs": [
            {
              "text": "•",
              "schriftgröße": 18.0,
              "schriftart": "ArialMT",
              "farbe": "#000000",
              "bold": false,
              "italic": false,
              "underline": null
            },
            {
              "text": " Nutzung agiler Projektmanagementmethoden ermöglicht eine flexible Entwicklung und schnelle Anpassung an ",
              "schriftgröße": 18.0,
              "schriftart": "TimesNewRomanPSMT",
              "farbe": "#000000",
              "bold": false,
              "italic": false,
              "underline": null
            }
          ],
          "plain_text": "• Nutzung agiler Projektmanagementmethoden ermöglicht eine flexible Entwicklung und schnelle Anpassung an"
        }
      ],
      "z_index": 7,
      "position": {
        "links": 44.06399917602539,
        "oben": 340.9700012207031,
        "breite": 822.2222557067871,
        "höhe": 20.178009033203125
      }
    },
    {
      "typ": "text",
      "inhalt": "neue Anforderungen oder Erkenntnisse.",
      "paragraphs": [
        {
          "level": 0,
          "is_bullet": false,
          "textausrichtung": "left",
          "runs": [
            {
              "text": "neue Anforderungen oder Erkenntnisse.",
              "schriftgröße": 18.0,
              "schriftart": "TimesNewRomanPSMT",
              "farbe": "#000000",
              "bold": false,
              "italic": false,
              "underline": null
            }
          ],
          "plain_text": "neue Anforderungen oder Erkenntnisse."
        }
      ],
      "z_index": 8,
      "position": {
        "links": 62.06399917602539,
        "oben": 362.8219909667969,
        "breite": 285.98403549194336,
        "höhe": 19.925994873046875
      }
    },
    {
      "typ": "text",
      "inhalt": "• Kontinuierliche Optimierung der Prozesse stellt sicher, dass Datenanalyse langfristig effizient bleibt und sich an",
      "paragraphs": [
        {
          "level": 0,
          "is_bullet": true,
          "textausrichtung": "center",
          "runs": [
            {
              "text": "•",
              "schriftgröße": 18.0,
              "schriftart": "ArialMT",
              "farbe": "#000000",
              "bold": false,
              "italic": false,
              "underline": null
            },
            {
              "text": " Kontinuierliche Optimierung der Prozesse stellt sicher, dass Datenanalyse langfristig effizient bleibt und sich an ",
              "schriftgröße": 18.0,
              "schriftart": "TimesNewRomanPSMT",
              "farbe": "#000000",
              "bold": false,
              "italic": false,
              "underline": null
            }
          ],
          "plain_text": "• Kontinuierliche Optimierung der Prozesse stellt sicher, dass Datenanalyse langfristig effizient bleibt und sich an"
        }
      ],
      "z_index": 9,
      "position": {
        "links": 44.06399917602539,
        "oben": 394.1299743652344,
        "breite": 829.1167869567871,
        "höhe": 20.178009033203125
      }
    },
    {
      "typ": "text",
      "inhalt": "veränderte Geschäftsbedingungen anpassen kann.",
      "paragraphs": [
        {
          "level": 0,
          "is_bullet": false,
          "textausrichtung": "left",
          "runs": [
            {
              "text": "veränderte Geschäftsbedingungen anpassen kann.",
              "schriftgröße": 18.0,
              "schriftart": "TimesNewRomanPSMT",
              "farbe": "#000000",
              "bold": false,
              "italic": false,
              "underline": null
            }
          ],
          "plain_text": "veränderte Geschäftsbedingungen anpassen kann."
        }
      ],
      "z_index": 10,
      "position": {
        "links": 62.06399917602539,
        "oben": 415.98199462890625,
        "breite": 357.87609481811523,
        "höhe": 19.925994873046875
      }
    }
  ],
  "semantik": {
    "segmentierung": {
      "abschnitte": [
        "Implementierungsstrategie\nImplementierungsstrategie\nDie erfolgreiche Einführung von Big Data erfordert strukturierte Planung und agile Umsetzung. Technologische\nIntegration muss mit Geschäftsprozessen harmonieren.\n• Klare Zieldefinition vor Projektstart hilft Unternehmen dabei, den Nutzen von Datenprojekten messbar zu\nmachen und Prioritäten festzulegen.\n• Auswahl geeigneter Technologien und Partner ist entscheidend, um leistungsfähige Analyseplattformen und\neine stabile Dateninfrastruktur aufzubauen.\n• Nutzung agiler Projektmanagementmethoden ermöglicht eine flexible Entwicklung und schnelle Anpassung an\nneue Anforderungen oder Erkenntnisse.\n• Kontinuierliche Optimierung der Prozesse stellt sicher, dass Datenanalyse langfristig effizient bleibt und sich an\nveränderte Geschäftsbedingungen anpassen kann."
      ],
      "saetze": [
        "Implementierungsstrategie",
        "Implementierungsstrategie",
        "Die erfolgreiche Einführung von Big Data erfordert strukturierte Planung und agile Umsetzung.",
        "Technologische",
        "Integration muss mit Geschäftsprozessen harmonieren.",
        "Klare Zieldefinition vor Projektstart hilft Unternehmen dabei, den Nutzen von Datenprojekten messbar zu",
        "machen und Prioritäten festzulegen.",
        "Auswahl geeigneter Technologien und Partner ist entscheidend, um leistungsfähige Analyseplattformen und",
        "eine stabile Dateninfrastruktur aufzubauen.",
        "Nutzung agiler Projektmanagementmethoden ermöglicht eine flexible Entwicklung und schnelle Anpassung an",
        "neue Anforderungen oder Erkenntnisse.",
        "Kontinuierliche Optimierung der Prozesse stellt sicher, dass Datenanalyse langfristig effizient bleibt und sich an",
        "veränderte Geschäftsbedingungen anpassen kann."
      ]
    },
    "textkomplexitaet": {
      "wortanzahl": 85,
      "satzanzahl": 13,
      "durchschnitt_wortlaenge": 8.376,
      "durchschnitt_satzlaenge_woerter": 6.538,
      "type_token_ratio": 0.894
    },
    "keywords": [
      "implementierungsstrategie erfolgreiche",
      "implementierungsstrategie",
      "implementierungsstrategie implementierungsstrategie",
      "nutzen datenprojekten",
      "agiler projektmanagementmethoden",
      "projektmanagementmethoden ermöglicht",
      "projektmanagementmethoden",
      "planung agile",
      "datenprojekten",
      "strukturierte planung"
    ],
    "embeddings": {
      "ueberschrift": [
        -0.07826220989227295,
        0.14625360071659088,
        -0.25663307309150696,
        -0.266635924577713,
        -0.08638104051351547,
        -0.08083406835794449,
        -0.06792425364255905,
        -0.07931701838970184,
        -0.3794404864311218,
        0.2773188054561615,
        0.12877878546714783,
        0.583446204662323,
        0.04903951659798622,
        -0.3218659460544586,
        0.25128793716430664,
        0.02399621717631817,
        -0.2660888731479645,
        -0.1946546733379364,
        -0.014861710369586945,
        0.01980564184486866,
        0.0893494114279747,
        -0.3734509348869324,
        -0.027611924335360527,
        -0.19988930225372314,
        -0.1834089756011963,
        0.06415312737226486,
        -0.15688923001289368,
        -0.23123493790626526,
        0.10493622720241547,
        -0.3992757797241211,
        0.1329094022512436,
        0.014852589927613735,
        0.3821069896221161,
        0.06131800636649132,
        -0.10393991321325302,
        0.09282447397708893,
        0.1357843577861786,
        0.0921507477760315,
        -0.1372721642255783,
        0.021856294944882393,
        -0.12888343632221222,
        0.01943741738796234,
        0.0341976135969162,
        0.10154446214437485,
        -0.20113465189933777,
        -0.15076403319835663,
        -0.13790194690227509,
        -0.11501192301511765,
        -0.6481090188026428,
        -0.03653756156563759,
        -0.2583531141281128,
        -0.40686437487602234,
        -0.017220379784703255,
        -0.5154111981391907,
        0.17240837216377258,
        0.3461471199989319,
        0.5577331185340881,
        0.3022904098033905,
        -0.007953694090247154,
        -0.12333858013153076,
        0.1752522885799408,
        0.10706525295972824,
        -0.38320451974868774,
        0.025743450969457626,
        0.04739859327673912,
        0.1403096318244934,
        0.060622360557317734,
        0.35002121329307556,
        0.022396882995963097,
        -0.01752588525414467,
        -0.40016815066337585,
        0.013299738988280296,
        0.022337349131703377,
        -0.1030583381652832,
        -0.24558039009571075,
        -0.059269633144140244,
        0.07812024652957916,
        0.3252010941505432,
        0.39736905694007874,
        0.0034912696573883295,
        0.2928144037723541,
        0.0867529883980751,
        0.038473207503557205,
        0.12372107058763504,
        0.11434989422559738,
        0.19526532292366028,
        -0.13745340704917908,
        0.0010921572102233768,
        0.23615662753582,
        -0.13944153487682343,
        0.08673636615276337,
        -0.10708779841661453,
        0.1471172422170639,
        -0.30233803391456604,
        0.2216012179851532,
        0.22812771797180176,
        -0.07131605595350266,
        -0.22415821254253387,
        -0.11818565428256989,
        1.5342216491699219,
        -0.08831769227981567,
        -0.09345424175262451,
        0.06561239063739777,
        -0.25585752725601196,
        -0.0037566509563475847,
        -0.013168500736355782,
        -0.021936386823654175,
        -0.17064471542835236,
        0.06406290084123611,
        0.016873808577656746,
        -0.044729944318532944,
        0.10492163151502609,
        -0.3946246802806854,
        -0.5121597051620483,
        -0.14111194014549255,
        -0.009464964270591736,
        -0.11464958637952805,
        0.12000961601734161,
        0.031616516411304474,
        0.27855798602104187,
        -0.08667244017124176,
        -0.23191246390342712,
        0.3705469071865082,
        0.044242698699235916,
        -0.03680530562996864,
        -0.13476331532001495,
        -0.03670891001820564,
        -0.4145095646381378,
        -0.4746525287628174,
        -0.1661362648010254,
        0.05337458476424217,
        -0.1502997875213623,
        -0.4565519690513611,
        -0.10905607789754868,
        0.06485934555530548,
        -0.13202042877674103,
        0.2291431725025177,
        -0.2986025810241699,
        0.23294998705387115,
        0.043328650295734406,
        0.019557062536478043,
        0.3206411898136139,
        0.5087360143661499,
        -0.003025648882612586,
        0.242463618516922,
        0.5296682119369507,
        0.3403458893299103,
        -0.19873200356960297,
        0.21795395016670227,
        -0.08717815577983856,
        0.17551986873149872,
        -0.13149887323379517,
        0.21721410751342773,
        0.044088173657655716,
        -0.16405163705348969,
        0.13485375046730042,
        -0.4720321297645569,
        -0.07223427295684814,
        0.2900007665157318,
        0.19039173424243927,
        -0.45302364230155945,
        0.10255979001522064,
        0.1063627228140831,
        -0.32194873690605164,
        -0.21125176548957825,
        -0.1022879108786583,
        -0.23539112508296967,
        -0.453153520822525,
        0.05274990573525429,
        0.13020126521587372,
        0.22167864441871643,
        -0.05847453325986862,
        0.2285577952861786,
        -0.12868057191371918,
        0.0831872746348381,
        -0.03632868081331253,
        0.357234388589859,
        -0.35350099205970764,
        0.154120072722435,
        -0.11088471114635468,
        0.6116431355476379,
        -0.06659682095050812,
        0.20811231434345245,
        -0.24653682112693787,
        -0.19223691523075104,
        -0.1692434698343277,
        0.1964811533689499,
        0.1837228685617447,
        -0.06923796981573105,
        -0.035413958132267,
        -0.4283317029476166,
        0.09333290904760361,
        0.0446191169321537,
        0.026739919558167458,
        -0.29057154059410095,
        -0.3538849651813507,
        0.2903968393802643,
        -0.10595415532588959,
        0.20853160321712494,
        0.11733918637037277,
        -0.13173671066761017,
        0.2177080363035202,
        -0.3702377676963806,
        0.1587836742401123,
        -0.09919820725917816,
        0.029529204592108727,
        0.06352052837610245,
        -0.28738933801651,
        -0.11914604902267456,
        -0.06392217427492142,
        0.10404015332460403,
        0.11782405525445938,
        0.09696696698665619,
        0.05310526490211487,
        0.09804366528987885,
        0.2927745282649994,
        0.07652520388364792,
        0.21336449682712555,
        -0.4251399040222168,
        0.21051748096942902,
        -0.08848050981760025,
        0.46799060702323914,
        0.5512322783470154,
        -0.33338356018066406,
        0.09893293678760529,
        0.24350683391094208,
        -0.24849285185337067,
        -0.30078649520874023,
        0.08399896323680878,
        0.07673382759094238,
        -0.3036980926990509,
        -0.7395572662353516,
        0.5462629199028015,
        -0.019709985703229904,
        -0.5066035389900208,
        -0.14682070910930634,
        0.35127705335617065,
        0.1138303130865097,
        -0.3989085257053375,
        -0.2626156508922577,
        0.09385719150304794,
        -0.5567842125892639,
        -0.03680004924535751,
        0.20452168583869934,
        0.014714485965669155,
        -0.10717009752988815,
        -0.35073116421699524,
        0.11256041377782822,
        0.06743032485246658,
        0.2642143666744232,
        -0.07324886322021484,
        -0.18952162563800812,
        0.34324195981025696,
        -0.010578732006251812,
        -0.20125241577625275,
        -0.1107080802321434,
        -0.11524774879217148,
        -0.22656552493572235,
        -0.1278311163187027,
        0.4409133791923523,
        0.022577306255698204,
        -0.1447720229625702,
        0.010917482897639275,
        0.28850215673446655,
        0.2777881324291229,
        -0.34253591299057007,
        -0.3606797158718109,
        0.1549888402223587,
        0.13316260278224945,
        0.1913255900144577,
        0.013042493723332882,
        -0.05652478709816933,
        -0.03125423938035965,
        0.08814084529876709,
        0.06831729412078857,
        -0.03945794329047203,
        0.03546397015452385,
        -0.39785441756248474,
        0.24476264417171478,
        0.29259222745895386,
        0.189732626080513,
        -0.1122496947646141,
        -0.20060290396213531,
        0.10158009827136993,
        -0.09143949300050735,
        0.23588848114013672,
        0.34934964776039124,
        -0.019948897883296013,
        -0.13650067150592804,
        0.10460803657770157,
        0.10199720412492752,
        0.204005628824234,
        -0.0019382472382858396,
        -0.5131862759590149,
        -0.17625008523464203,
        0.14865946769714355,
        -0.19236032664775848,
        -0.05354980751872063,
        -0.27406564354896545,
        -0.13191641867160797,
        0.20512835681438446,
        -0.41986969113349915,
        0.04441918060183525,
        0.09374605864286423,
        -0.1933991014957428,
        -0.20569919049739838,
        0.23222553730010986,
        -0.10619612783193588,
        0.19810417294502258,
        -0.07566665858030319,
        0.08660797774791718,
        -0.4024703800678253,
        0.059879839420318604,
        0.1151486411690712,
        -0.14625251293182373,
        0.014349929988384247,
        0.08028791844844818,
        -0.027487458661198616,
        0.1498919278383255,
        -0.5238703489303589,
        0.059756021946668625,
        0.04458301514387131,
        0.19250093400478363,
        0.05696706101298332,
        0.20143716037273407,
        0.32816216349601746,
        -0.09925772994756699,
        -0.11442463845014572,
        0.1933474987745285,
        0.007178472820669413,
        -0.0134068438783288,
        0.2333153933286667,
        0.33309540152549744,
        0.042048610746860504,
        -0.3036139905452728,
        0.15449108183383942,
        -0.14933578670024872,
        0.4530164897441864,
        -0.2770650386810303,
        -0.04826279729604721,
        0.6320855021476746,
        0.24929378926753998,
        -0.5139305591583252,
        -0.11291263997554779,
        0.019388869404792786,
        -0.4119738042354584,
        0.15490508079528809,
        0.24425815045833588,
        -0.01900543086230755,
        0.3358997404575348,
        0.015152433887124062,
        0.12636859714984894,
        0.05614545941352844,
        -0.027553727850317955,
        -0.023723218590021133,
        0.09190459549427032,
        0.1364436000585556,
        0.28222987055778503,
        0.10303066670894623,
        -0.0739358440041542,
        -0.1624077558517456,
        0.5283271074295044,
        -0.1348082572221756,
        0.24758335947990417,
        -0.18564380705356598,
        -0.3032205402851105,
        -0.3153529465198517,
        -0.05272972583770752,
        0.2632676959037781,
        0.20501820743083954,
        -0.11251480877399445,
        0.08550820499658585,
        0.02763775922358036,
        0.3647599518299103,
        0.32906660437583923,
        0.07872773706912994,
        0.10842233151197433,
        -0.008314709179103374,
        -0.1477878838777542,
        -0.06147034838795662,
        -0.1774756759405136,
        -0.18927045166492462,
        0.08181167393922806,
        0.45338138937950134
      ],
      "fliesstext": [
        0.05741997808218002,
        0.17083893716335297,
        -0.16642479598522186,
        -0.18802513182163239,
        0.036929525434970856,
        -0.13488584756851196,
        -0.1989862620830536,
        -0.043291304260492325,
        -0.2327418476343155,
        0.16631324589252472,
        0.02873329073190689,
        0.18750064074993134,
        0.2910531163215637,
        -0.31386664509773254,
        0.09177982062101364,
        -0.03732772916555405,
        -0.0867043286561966,
        -0.1476684957742691,
        -0.1327701359987259,
        0.00765183474868536,
        -0.26436498761177063,
        -0.2957676947116852,
        0.09539031982421875,
        -0.19084957242012024,
        -0.16491377353668213,
        0.12720613181591034,
        -0.052924174815416336,
        -0.07134778797626495,
        0.13935577869415283,
        -0.19238810241222382,
        0.14395101368427277,
        0.0967431291937828,
        0.17894062399864197,
        0.04849832504987717,
        -0.0676690936088562,
        0.12633350491523743,
        0.017055436968803406,
        -0.08342061936855316,
        -0.03525566682219505,
        0.0003437554696574807,
        -0.061229486018419266,
        -0.07072998583316803,
        0.13482171297073364,
        -0.09710227698087692,
        -0.1121940016746521,
        -0.07391128689050674,
        -0.16012711822986603,
        0.0483124814927578,
        -0.4343704283237457,
        0.08798647671937943,
        -0.20653900504112244,
        -0.3788532614707947,
        0.0012167859822511673,
        -0.0435614213347435,
        -0.019780103117227554,
        0.2542158365249634,
        0.15972217917442322,
        0.14771008491516113,
        -0.039269499480724335,
        -0.10350334644317627,
        0.09198128432035446,
        -0.0005791806615889072,
        0.009461130946874619,
        0.027540046721696854,
        0.1717548668384552,
        0.16469213366508484,
        -0.05869975686073303,
        0.1346459984779358,
        -0.058434296399354935,
        0.0642785131931305,
        -0.033941611647605896,
        0.05008325353264809,
        -0.251585453748703,
        0.008279664441943169,
        -0.19379572570323944,
        0.02393505722284317,
        -0.0070357536897063255,
        0.14902091026306152,
        0.2293160855770111,
        0.016985751688480377,
        0.03399782255291939,
        -0.0032577994279563427,
        -0.09696419537067413,
        0.0022911294363439083,
        -0.004459382500499487,
        0.017934385687112808,
        -0.0267384871840477,
        0.04971691220998764,
        0.05297958105802536,
        -0.08397043496370316,
        0.10203943401575089,
        0.13201706111431122,
        -0.0865006074309349,
        -0.004022565204650164,
        -0.09291192144155502,
        0.024776669219136238,
        -0.03479836508631706,
        -0.04728303849697113,
        -0.055481135845184326,
        0.38928478956222534,
        -0.12443313002586365,
        -0.12623320519924164,
        -0.1439216136932373,
        -0.16168540716171265,
        0.21498054265975952,
        -0.017305772751569748,
        0.06048161908984184,
        -0.10721348226070404,
        0.10653894394636154,
        0.03994538262486458,
        0.06722915917634964,
        0.1589149534702301,
        -0.12145514786243439,
        -0.10034752637147903,
        0.10499247163534164,
        0.11179281771183014,
        -0.18185286223888397,
        0.026906456798315048,
        -0.03852584958076477,
        -0.13210566341876984,
        0.0005961130373179913,
        -0.03517964482307434,
        0.1400219202041626,
        0.004464075434952974,
        0.08752062171697617,
        0.08360719680786133,
        -0.08942124992609024,
        -0.16617994010448456,
        -0.18818923830986023,
        -0.1712077409029007,
        0.14157192409038544,
        -0.026380201801657677,
        -0.10714308172464371,
        -0.003194392193108797,
        -0.08220682293176651,
        -0.05750812217593193,
        0.0187571682035923,
        -0.06667177379131317,
        -0.0670526996254921,
        0.15701310336589813,
        0.09756819903850555,
        0.28046929836273193,
        0.48717057704925537,
        -0.012809603475034237,
        0.11005087196826935,
        0.3046237528324127,
        0.15329161286354065,
        -0.09336957335472107,
        0.10066718608140945,
        -0.18502181768417358,
        0.17357584834098816,
        -0.039451029151678085,
        0.29135948419570923,
        0.003894404973834753,
        -0.01815309375524521,
        0.013733712956309319,
        -0.08263015747070312,
        -0.1193755716085434,
        -0.01492253877222538,
        0.0006023137830197811,
        -0.1887456625699997,
        0.1727682650089264,
        -0.027270467951893806,
        -0.16822832822799683,
        -0.24380896985530853,
        -0.1946370005607605,
        -0.18526983261108398,
        -0.1582118570804596,
        0.24032530188560486,
        0.11805476248264313,
        -0.022212844341993332,
        -0.14413973689079285,
        0.11992843449115753,
        -0.18366967141628265,
        0.1866021454334259,
        -0.07895823568105698,
        0.14849838614463806,
        -0.19345968961715698,
        0.07709567248821259,
        -0.1490148901939392,
        0.40112799406051636,
        -0.02894105389714241,
        0.22180581092834473,
        -0.15642379224300385,
        0.018838942050933838,
        -0.18841861188411713,
        0.05372084677219391,
        0.14562271535396576,
        -0.06422659009695053,
        0.04062914848327637,
        -0.1944907158613205,
        0.32225561141967773,
        0.2722821533679962,
        0.03383459150791168,
        -0.05020470544695854,
        -0.21151943504810333,
        0.29885333776474,
        0.026194702833890915,
        0.1094164252281189,
        -0.17637084424495697,
        -0.11081413179636002,
        0.033800676465034485,
        -0.26679494976997375,
        0.055440522730350494,
        -0.10826057940721512,
        -0.026875102892518044,
        0.2983422577381134,
        0.041848428547382355,
        -0.09100449085235596,
        0.08912406861782074,
        -0.1075768768787384,
        -0.006018149666488171,
        -0.21649973094463348,
        0.15498314797878265,
        -0.08769552409648895,
        -0.12571340799331665,
        -0.06291484832763672,
        0.041463591158390045,
        -0.20892281830310822,
        0.15672501921653748,
        -0.08706843852996826,
        0.19892144203186035,
        0.09795789420604706,
        -0.1790202111005783,
        -0.08658882975578308,
        0.06590224802494049,
        -0.014784397557377815,
        -0.03189206123352051,
        0.13866694271564484,
        0.014723116531968117,
        -0.16851283609867096,
        -0.4989570379257202,
        0.16094937920570374,
        0.11932496726512909,
        -0.29974424839019775,
        -0.03728688508272171,
        0.11273382604122162,
        -0.12428553402423859,
        -0.15772737562656403,
        -0.12051025778055191,
        0.06773430854082108,
        -0.2519910931587219,
        0.03549712523818016,
        0.025719599798321724,
        0.09917120635509491,
        -0.13115613162517548,
        -0.23930002748966217,
        -0.09060519933700562,
        0.030640525743365288,
        0.1424136757850647,
        -0.12489976733922958,
        -0.20904479920864105,
        0.08687888085842133,
        0.008903278037905693,
        -0.19894638657569885,
        -0.0775151476264,
        -0.23483623564243317,
        -0.09058130532503128,
        0.0021962644532322884,
        0.19149497151374817,
        0.20075646042823792,
        -0.2585773766040802,
        0.06329002976417542,
        0.2799595594406128,
        0.011601489968597889,
        -0.09777550399303436,
        -0.2382957637310028,
        0.03096114657819271,
        -0.030447492375969887,
        0.15028491616249084,
        -0.06929826736450195,
        0.24535803496837616,
        -0.0749024897813797,
        0.08118674904108047,
        0.08973465859889984,
        0.054809145629405975,
        0.004939212929457426,
        -0.27493834495544434,
        0.11406037211418152,
        0.06247569993138313,
        0.2328435182571411,
        0.0997161865234375,
        -0.06293364614248276,
        0.06003374233841896,
        -0.06140422448515892,
        -0.0929441899061203,
        0.2151142805814743,
        0.005524056032299995,
        -0.0010158512741327286,
        0.12145553529262543,
        0.1729317158460617,
        0.08432763069868088,
        -0.2001100480556488,
        -0.18525011837482452,
        -0.034682683646678925,
        -0.16166812181472778,
        0.05218289792537689,
        -0.012509441934525967,
        -0.15521229803562164,
        -0.14580796658992767,
        0.04756304621696472,
        -0.11138126999139786,
        0.07844419777393341,
        0.037103425711393356,
        0.0007727602496743202,
        -0.17788080871105194,
        0.10841301083564758,
        0.03604483976960182,
        0.13207949697971344,
        0.12640279531478882,
        0.05166831612586975,
        -0.3702356815338135,
        -0.014628024771809578,
        0.17908304929733276,
        -0.17844408750534058,
        0.03586471080780029,
        -0.11848918348550797,
        0.15566381812095642,
        -0.016280008479952812,
        -0.1921623945236206,
        -0.04730452224612236,
        0.09794334322214127,
        -0.022670643404126167,
        -0.02519010193645954,
        0.23569050431251526,
        -0.014335181564092636,
        -0.21917837858200073,
        0.30018410086631775,
        0.10770265758037567,
        -0.05531596392393112,
        0.0987720638513565,
        -0.010442721657454967,
        0.02375582978129387,
        0.027872826904058456,
        -0.05180633068084717,
        0.09193584322929382,
        0.05295926332473755,
        0.2836931347846985,
        -0.12673711776733398,
        -0.0865752249956131,
        0.3802260756492615,
        0.0908440575003624,
        -0.4124417304992676,
        -0.034890349954366684,
        0.0908082127571106,
        -0.0991702601313591,
        0.16160815954208374,
        0.38172799348831177,
        -0.0012836991809308529,
        0.040393028408288956,
        0.04214977100491524,
        0.08926598727703094,
        0.09591197222471237,
        -0.028287431225180626,
        0.2257479727268219,
        0.037226058542728424,
        0.053198013454675674,
        0.20474039018154144,
        -0.029697470366954803,
        -0.08368780463933945,
        -0.043079618364572525,
        0.33871105313301086,
        -0.06664300709962845,
        0.08671499788761139,
        -0.1126226857304573,
        -0.15985845029354095,
        -0.04172559455037117,
        -0.019098838791251183,
        0.20264367759227753,
        0.13480667769908905,
        -0.18566656112670898,
        -0.07129965722560883,
        0.05456700176000595,
        0.260448157787323,
        0.06322706490755081,
        0.11770087480545044,
        0.07059884816408157,
        0.09539729356765747,
        0.07861550897359848,
        0.0999862402677536,
        -0.02492232248187065,
        0.036879170686006546,
        0.05842551961541176,
        0.022935036569833755
      ]
    },
    "cosine": {
      "ueberschrift_vs_fliesstext": 0.698969
    },
    "language_mode": "mixed",
    "zusammenfassung": {
      "modus": "t5",
      "wortanzahl": 85,
      "kurzer_originaltext": "",
      "summary": "implementationsstrategie Implementierungsstrategie Die erfolgreiche Einführung von Big Data erfordert strukturierte Planung und agile Umsetzung . klare Zieldefinition vor Projektstart hilft Unternehmen dabei, den Nutzen von Datenprojekten messbar zu machen und Prioritäten festzulegen .",
      "modell": "t5-small"
    },
    "pfade": {
      "json_datei": "data\\processed\\pdf_slide_036.json",
      "assets_verzeichnis": "export\\assets"
    }
  }
}