{
  "foliennummer": 26,
  "überschrift": "Herausforderungen bei der Implementierung",
  "canvas": {
    "width": 9144000,
    "height": 5143500,
    "unit": "emu"
  },
  "elemente": [
    {
      "typ": "text",
      "inhalt": "Kernaussage: Die Einführung von KI-Avataren ist mehr als ein Tool-Kauf, weil Prozesse, Systeme und Qualitätskontrollen angepasst werden müssen. Technische Integration und organisatorische Verantwortung sind zentrale Erfolgsfaktoren.\n\nSysteme müssen in bestehende IT- und CRM-Strukturen integriert werden.\nEchtzeit-Rendering benötigt leistungsfähige Infrastruktur.\nQualitätssicherung verhindert diskriminierende oder falsche Inhalte.\nMonitoring und Qualitätssicherung sind wichtig, um Halluzinationen, Bias oder unpassende Antworten früh zu erkennen.",
      "paragraphs": [
        {
          "level": 0,
          "is_bullet": false,
          "textausrichtung": null,
          "zeilenabstand": null,
          "abstand_vor": null,
          "abstand_nach": null,
          "runs": [
            {
              "text": "Kernaussage: ",
              "schriftgröße": null,
              "schriftart": "Times New Roman",
              "farbe": "FF0000",
              "bold": null,
              "italic": null,
              "underline": null
            },
            {
              "text": "Die Einführung von KI-Avataren ist mehr als ein Tool-Kauf, weil Prozesse, Systeme und Qualitätskontrollen angepasst werden müssen. Technische Integration und organisatorische Verantwortung sind zentrale Erfolgsfaktoren.",
              "schriftgröße": null,
              "schriftart": "Times New Roman",
              "farbe": null,
              "bold": null,
              "italic": null,
              "underline": null
            }
          ],
          "plain_text": "Kernaussage: Die Einführung von KI-Avataren ist mehr als ein Tool-Kauf, weil Prozesse, Systeme und Qualitätskontrollen angepasst werden müssen. Technische Integration und organisatorische Verantwortung sind zentrale Erfolgsfaktoren."
        },
        {
          "level": 0,
          "is_bullet": true,
          "textausrichtung": null,
          "zeilenabstand": null,
          "abstand_vor": null,
          "abstand_nach": null,
          "runs": [
            {
              "text": "Systeme müssen in bestehende IT- und CRM-Strukturen integriert werden.",
              "schriftgröße": null,
              "schriftart": "Times New Roman",
              "farbe": null,
              "bold": null,
              "italic": null,
              "underline": null
            }
          ],
          "plain_text": "Systeme müssen in bestehende IT- und CRM-Strukturen integriert werden."
        },
        {
          "level": 0,
          "is_bullet": true,
          "textausrichtung": null,
          "zeilenabstand": null,
          "abstand_vor": null,
          "abstand_nach": null,
          "runs": [
            {
              "text": "Echtzeit-Rendering benötigt leistungsfähige Infrastruktur.",
              "schriftgröße": null,
              "schriftart": "Times New Roman",
              "farbe": null,
              "bold": null,
              "italic": null,
              "underline": null
            }
          ],
          "plain_text": "Echtzeit-Rendering benötigt leistungsfähige Infrastruktur."
        },
        {
          "level": 0,
          "is_bullet": true,
          "textausrichtung": null,
          "zeilenabstand": null,
          "abstand_vor": null,
          "abstand_nach": null,
          "runs": [
            {
              "text": "Qualitätssicherung verhindert diskriminierende oder falsche Inhalte.",
              "schriftgröße": null,
              "schriftart": "Times New Roman",
              "farbe": null,
              "bold": null,
              "italic": null,
              "underline": null
            }
          ],
          "plain_text": "Qualitätssicherung verhindert diskriminierende oder falsche Inhalte."
        },
        {
          "level": 0,
          "is_bullet": true,
          "textausrichtung": null,
          "zeilenabstand": null,
          "abstand_vor": null,
          "abstand_nach": null,
          "runs": [
            {
              "text": "Monitoring und Qualitätssicherung sind wichtig, um Halluzinationen, Bias oder unpassende Antworten früh zu erkennen.",
              "schriftgröße": null,
              "schriftart": "Times New Roman",
              "farbe": null,
              "bold": null,
              "italic": null,
              "underline": null
            }
          ],
          "plain_text": "Monitoring und Qualitätssicherung sind wichtig, um Halluzinationen, Bias oder unpassende Antworten früh zu erkennen."
        }
      ],
      "schriftgröße": null,
      "schriftart": null,
      "farbe": null,
      "textausrichtung": null,
      "zeilenabstand": null,
      "abstand_vor": null,
      "abstand_nach": null,
      "listebene": 0,
      "z_index": 1,
      "position": {
        "links": 365760,
        "oben": 1426464,
        "breite": 8321040,
        "höhe": 3472106
      }
    },
    {
      "typ": "text",
      "inhalt": "Herausforderungen bei der Implementierung",
      "paragraphs": [
        {
          "level": 0,
          "is_bullet": false,
          "textausrichtung": null,
          "zeilenabstand": 1.0,
          "abstand_vor": null,
          "abstand_nach": null,
          "runs": [
            {
              "text": "Herausforderungen",
              "schriftgröße": 30.0,
              "schriftart": "Times New Roman",
              "farbe": null,
              "bold": null,
              "italic": null,
              "underline": null
            },
            {
              "text": " ",
              "schriftgröße": 30.0,
              "schriftart": "Times New Roman",
              "farbe": null,
              "bold": null,
              "italic": null,
              "underline": null
            },
            {
              "text": "bei",
              "schriftgröße": 30.0,
              "schriftart": "Times New Roman",
              "farbe": null,
              "bold": null,
              "italic": null,
              "underline": null
            },
            {
              "text": " der ",
              "schriftgröße": 30.0,
              "schriftart": "Times New Roman",
              "farbe": null,
              "bold": null,
              "italic": null,
              "underline": null
            },
            {
              "text": "Implementierung",
              "schriftgröße": 30.0,
              "schriftart": "Times New Roman",
              "farbe": null,
              "bold": null,
              "italic": null,
              "underline": null
            }
          ],
          "plain_text": "Herausforderungen bei der Implementierung"
        }
      ],
      "schriftgröße": null,
      "schriftart": null,
      "farbe": null,
      "textausrichtung": null,
      "zeilenabstand": null,
      "abstand_vor": null,
      "abstand_nach": null,
      "listebene": 0,
      "z_index": 2,
      "position": {
        "links": 365760,
        "oben": 429768,
        "breite": 8301600,
        "höhe": 816429
      }
    }
  ],
  "semantik": {
    "segmentierung": {
      "abschnitte": [
        "Herausforderungen bei der Implementierung\nKernaussage: Die Einführung von KI-Avataren ist mehr als ein Tool-Kauf, weil Prozesse, Systeme und Qualitätskontrollen angepasst werden müssen. Technische Integration und organisatorische Verantwortung sind zentrale Erfolgsfaktoren.",
        "Systeme müssen in bestehende IT- und CRM-Strukturen integriert werden.\nEchtzeit-Rendering benötigt leistungsfähige Infrastruktur.\nQualitätssicherung verhindert diskriminierende oder falsche Inhalte.\nMonitoring und Qualitätssicherung sind wichtig, um Halluzinationen, Bias oder unpassende Antworten früh zu erkennen.\nHerausforderungen bei der Implementierung"
      ],
      "saetze": [
        "Herausforderungen bei der Implementierung",
        "Kernaussage:",
        "Die Einführung von KI-Avataren ist mehr als ein Tool-Kauf, weil Prozesse, Systeme und Qualitätskontrollen angepasst werden müssen.",
        "Technische Integration und organisatorische Verantwortung sind zentrale Erfolgsfaktoren.",
        "Systeme müssen in bestehende IT- und CRM-Strukturen integriert werden.",
        "Echtzeit-Rendering benötigt leistungsfähige Infrastruktur.",
        "Qualitätssicherung verhindert diskriminierende oder falsche Inhalte.",
        "Monitoring und Qualitätssicherung sind wichtig, um Halluzinationen, Bias oder unpassende Antworten früh zu erkennen.",
        "Herausforderungen bei der Implementierung"
      ]
    },
    "textkomplexitaet": {
      "wortanzahl": 71,
      "satzanzahl": 9,
      "durchschnitt_wortlaenge": 7.746,
      "durchschnitt_satzlaenge_woerter": 7.889,
      "type_token_ratio": 0.817
    },
    "keywords": [
      "bei implementierung",
      "müssen technische",
      "implementierung kernaussage",
      "systeme müssen",
      "erfolgsfaktoren systeme",
      "benötigt leistungsfähige",
      "weil prozesse",
      "implementierung",
      "leistungsfähige infrastruktur",
      "infrastruktur qualitätssicherung"
    ],
    "embeddings": {
      "ueberschrift": [
        -0.03057219833135605,
        -0.043252669274806976,
        -0.050182145088911057,
        -0.04470307379961014,
        -0.06499148905277252,
        -0.05604684352874756,
        -0.31133559346199036,
        -0.04601544886827469,
        -0.23671157658100128,
        0.2756659984588623,
        -0.0955689325928688,
        0.27978286147117615,
        0.08170013129711151,
        -0.22242125868797302,
        0.32402095198631287,
        0.16577644646167755,
        -0.1043495312333107,
        -0.14802098274230957,
        -0.005116096697747707,
        0.18171797692775726,
        -0.03268352523446083,
        -0.4424531161785126,
        -0.005852023139595985,
        -0.23403865098953247,
        -0.12968996167182922,
        -0.045461781322956085,
        -0.08725501596927643,
        -0.08390899747610092,
        0.23374076187610626,
        -0.4356851577758789,
        -0.002436744049191475,
        -0.025621088221669197,
        0.3342590630054474,
        0.043814387172460556,
        -0.007089532446116209,
        0.04595436155796051,
        0.0705648884177208,
        0.04708315432071686,
        -0.09121553599834442,
        -0.03252151235938072,
        -0.01339028961956501,
        -0.10924794524908066,
        -0.08514995872974396,
        -0.037771206349134445,
        -0.06368348747491837,
        -0.21965990960597992,
        0.045744389295578,
        -0.005155046936124563,
        -0.6107600331306458,
        -0.005000588018447161,
        -0.4131569266319275,
        -0.334907203912735,
        0.12554559111595154,
        -0.398517370223999,
        -0.01101804617792368,
        0.17601487040519714,
        0.5328247547149658,
        0.10443902760744095,
        0.0647984966635704,
        0.06938037276268005,
        0.254827618598938,
        0.08395034074783325,
        -0.36665278673171997,
        0.24336053431034088,
        0.17604270577430725,
        0.0955939069390297,
        0.03329318389296532,
        0.24477878212928772,
        0.09433932602405548,
        0.01795179955661297,
        -0.5227940678596497,
        -0.021489456295967102,
        -0.06343239545822144,
        -0.2452545315027237,
        -0.13015428185462952,
        -0.20678812265396118,
        0.06427404284477234,
        0.24915042519569397,
        0.3922928273677826,
        -0.010632036253809929,
        0.3297370970249176,
        0.1787332147359848,
        0.11838000267744064,
        0.20559632778167725,
        -0.0008782031945884228,
        0.15232732892036438,
        -0.07409428805112839,
        0.058641791343688965,
        0.11537142843008041,
        -0.18666253983974457,
        -0.05740504339337349,
        -0.17579519748687744,
        0.24008247256278992,
        -0.20764456689357758,
        0.2573360204696655,
        0.03527866676449776,
        -0.04933200404047966,
        -0.170461043715477,
        -0.08546382188796997,
        1.329015851020813,
        -0.2384997010231018,
        0.1413237303495407,
        0.13961289823055267,
        -0.237300306558609,
        -0.08720887452363968,
        0.07082638889551163,
        0.08317849040031433,
        -0.41473880410194397,
        0.05118609592318535,
        0.05681915581226349,
        0.06687678396701813,
        0.08402658998966217,
        -0.34590139985084534,
        -0.1183498352766037,
        0.06167164817452431,
        -0.05804506689310074,
        -0.0601893812417984,
        -0.08482140302658081,
        0.024698568508028984,
        0.3197413682937622,
        -0.22995178401470184,
        -0.24484644830226898,
        0.23844559490680695,
        0.10451824218034744,
        0.13716769218444824,
        -0.04449811950325966,
        -0.13712303340435028,
        -0.31597575545310974,
        -0.1955057978630066,
        -0.08554854243993759,
        0.21155604720115662,
        -0.1279047131538391,
        -0.23143897950649261,
        0.007650324143469334,
        -0.007735390681773424,
        0.045990750193595886,
        0.3100307583808899,
        -0.3410751223564148,
        0.23353661596775055,
        0.0933014526963234,
        0.0540047250688076,
        0.22900688648223877,
        0.506598174571991,
        -0.03746015578508377,
        0.31869545578956604,
        0.4186234772205353,
        0.3529103398323059,
        0.04760150611400604,
        0.18651294708251953,
        -0.22958052158355713,
        0.3024737238883972,
        -0.15581831336021423,
        0.10246004164218903,
        0.21160675585269928,
        -0.10258322209119797,
        0.09583759307861328,
        -0.1750158667564392,
        -0.20386376976966858,
        0.14989568293094635,
        0.10546467453241348,
        -0.31489795446395874,
        0.09923169016838074,
        0.03906760364770889,
        -0.13977232575416565,
        -0.020845115184783936,
        -0.1825299859046936,
        -0.19579246640205383,
        -0.4661900997161865,
        0.025409149006009102,
        0.24258799850940704,
        0.15276028215885162,
        0.02832140028476715,
        0.3494168817996979,
        -0.21011251211166382,
        0.3988695740699768,
        -0.04897638037800789,
        0.21271158754825592,
        -0.043628014624118805,
        -0.03192221000790596,
        0.1658533364534378,
        0.4682016372680664,
        -0.23540689051151276,
        0.27136480808258057,
        -0.30575159192085266,
        -0.0018429188057780266,
        -0.18735162913799286,
        0.17815227806568146,
        0.17623990774154663,
        -0.19022871553897858,
        -0.12032325565814972,
        -0.31505224108695984,
        0.10470812022686005,
        0.00990336760878563,
        0.11990822106599808,
        -0.2847100496292114,
        -0.3505273759365082,
        0.2207101285457611,
        -0.1372978240251541,
        -0.08793909102678299,
        0.006456765346229076,
        -0.17399241030216217,
        0.20662809908390045,
        0.09414062649011612,
        0.15517200529575348,
        -0.14970408380031586,
        -0.05778485909104347,
        0.18755874037742615,
        -0.22883251309394836,
        -0.19524899125099182,
        -0.15976335108280182,
        0.06497173756361008,
        -0.04688633233308792,
        0.0817934200167656,
        -0.06405381858348846,
        -0.010343747213482857,
        0.07301798462867737,
        0.0692269578576088,
        0.15404316782951355,
        -0.33556893467903137,
        0.13676846027374268,
        -0.3303883969783783,
        0.4364158511161804,
        0.6167148351669312,
        -0.36486390233039856,
        -0.10857957601547241,
        0.06119723618030548,
        -0.4169468283653259,
        -0.15089061856269836,
        0.043005067855119705,
        0.12416292726993561,
        -0.03688604012131691,
        -0.8047674894332886,
        0.3949623107910156,
        0.003224696032702923,
        -0.5451041460037231,
        -0.02113628201186657,
        0.06854287534952164,
        0.27753859758377075,
        -0.40451276302337646,
        -0.27944543957710266,
        -0.10602578520774841,
        -0.2399844378232956,
        0.004616942256689072,
        0.10013222694396973,
        0.08838086575269699,
        0.05182761326432228,
        -0.15209925174713135,
        -0.06801895797252655,
        0.10821620374917984,
        0.4831104874610901,
        -0.2720474302768707,
        -0.37946346402168274,
        0.14186130464076996,
        0.0341077595949173,
        -0.24837778508663177,
        -0.07748933881521225,
        -0.2334139049053192,
        -0.13739457726478577,
        -0.09839046746492386,
        0.19090087711811066,
        0.1294889897108078,
        -0.05635262280702591,
        -0.04800834506750107,
        0.3250811696052551,
        0.4854716360569,
        -0.15705259144306183,
        -0.3714258372783661,
        0.12572996318340302,
        0.029971957206726074,
        0.31699544191360474,
        -0.11011634767055511,
        -0.17712348699569702,
        -0.098965123295784,
        0.1322469562292099,
        0.06696625798940659,
        -0.16916786134243011,
        0.10453800112009048,
        -0.4090106785297394,
        0.18244248628616333,
        0.20477882027626038,
        0.17903485894203186,
        -0.11576399207115173,
        -0.12111267447471619,
        0.0036043180152773857,
        -0.19888518750667572,
        0.2243189960718155,
        0.2745859920978546,
        -0.10177081823348999,
        -0.08594885468482971,
        0.17792025208473206,
        0.19186042249202728,
        0.1875726580619812,
        0.012663329020142555,
        -0.32123997807502747,
        -0.07648339122533798,
        -0.20077066123485565,
        -0.12877342104911804,
        -0.20453493297100067,
        -0.33487164974212646,
        0.23028893768787384,
        0.23261982202529907,
        -0.35150259733200073,
        -0.06663186848163605,
        -0.026333969086408615,
        -0.10249623656272888,
        -0.21389618515968323,
        0.1581835299730301,
        0.0049425289034843445,
        0.14151722192764282,
        -0.06525444239377975,
        0.2347651869058609,
        -0.4161444306373596,
        0.1976272463798523,
        0.07812589406967163,
        -0.1728208214044571,
        0.09092439711093903,
        -0.22654765844345093,
        0.05119965970516205,
        0.19888153672218323,
        -0.4647330939769745,
        0.05002196878194809,
        0.013923415914177895,
        -0.2890528738498688,
        -0.20577509701251984,
        0.23449523746967316,
        0.2627035975456238,
        -0.22704105079174042,
        -0.08419859409332275,
        0.12239490449428558,
        -0.007636550813913345,
        0.11519943922758102,
        0.14114223420619965,
        0.24278321862220764,
        -0.08442599326372147,
        -0.1900034099817276,
        0.11199785768985748,
        -0.043755240738391876,
        0.39017730951309204,
        -0.18555159866809845,
        -0.05868459865450859,
        0.5468488335609436,
        0.3618437945842743,
        -0.46119582653045654,
        0.07710988819599152,
        -0.06371975690126419,
        -0.31227219104766846,
        0.20199501514434814,
        0.17087170481681824,
        -0.11715526878833771,
        0.15671734511852264,
        0.1144348680973053,
        0.07428410649299622,
        -0.027276543900370598,
        0.032583627849817276,
        0.1213558241724968,
        0.010705599561333656,
        0.010713706724345684,
        0.17209145426750183,
        0.017830293625593185,
        -0.057344499975442886,
        -0.01601668819785118,
        0.5323441624641418,
        -0.20901580154895782,
        0.0881023183465004,
        -0.19649358093738556,
        -0.03119615465402603,
        -0.3296159505844116,
        -0.0006960155442357063,
        0.33102312684059143,
        0.15168139338493347,
        -0.09720537066459656,
        0.1312137246131897,
        0.004521943628787994,
        0.2102910429239273,
        0.20311607420444489,
        0.18938113749027252,
        0.007434442173689604,
        0.03828753903508186,
        -0.007447466254234314,
        0.05036880448460579,
        -0.023438693955540657,
        -0.0933491513133049,
        0.1168443113565445,
        0.3781090974807739
      ],
      "fliesstext": [
        -0.015149625018239021,
        -0.1121775358915329,
        -0.0005156600964255631,
        -0.09640901535749435,
        0.031672403216362,
        0.047102782875299454,
        -0.026356054469943047,
        -0.05779162421822548,
        0.07930709421634674,
        0.13486714661121368,
        0.06265222281217575,
        0.15857380628585815,
        0.16588249802589417,
        -0.029026901349425316,
        0.0023613472003489733,
        0.007638026960194111,
        -0.02998611517250538,
        -0.07412757724523544,
        -0.06987329572439194,
        -0.018248312175273895,
        -0.0309903547167778,
        -0.18600083887577057,
        0.07788756489753723,
        -0.035268232226371765,
        -0.10825716704130173,
        0.06508049368858337,
        -0.04244747757911682,
        -0.08310173451900482,
        -0.04699917510151863,
        -0.1279621422290802,
        -0.007607494480907917,
        -0.06931355595588684,
        0.16494359076023102,
        0.008369331248104572,
        -0.1991991400718689,
        0.08659476786851883,
        -0.011061682365834713,
        -0.028002647683024406,
        -0.08224038034677505,
        -0.14459486305713654,
        -0.07201860845088959,
        -0.05347263067960739,
        0.11138080060482025,
        -0.035788506269454956,
        0.0327916145324707,
        0.052794717252254486,
        -0.016767852008342743,
        -0.10198767483234406,
        -0.28973060846328735,
        -0.1313498169183731,
        -0.09900536388158798,
        -0.18375617265701294,
        0.08841100335121155,
        -0.06990955770015717,
        0.06358914077281952,
        0.06672944128513336,
        0.19849760830402374,
        -0.04236096516251564,
        -0.07809094339609146,
        -0.057694561779499054,
        0.08049912005662918,
        -0.10355513542890549,
        0.008022088557481766,
        0.042207859456539154,
        0.12331334501504898,
        0.012575635686516762,
        0.00406225211918354,
        -0.021020635962486267,
        0.051176462322473526,
        0.06814929842948914,
        -0.043190937489271164,
        -0.07617297768592834,
        -0.07553183287382126,
        -0.00015293777687475085,
        0.00664291437715292,
        0.08988458663225174,
        0.02911481447517872,
        -0.030341673642396927,
        0.2810744643211365,
        0.022064674645662308,
        0.18630385398864746,
        0.04293915629386902,
        0.15415805578231812,
        0.16064105927944183,
        -0.08799759298563004,
        0.09203740954399109,
        0.02144414559006691,
        -0.04927816241979599,
        0.026448983699083328,
        -0.050327807664871216,
        0.021222740411758423,
        0.01255948655307293,
        0.2122681736946106,
        -0.045309051871299744,
        0.16623373329639435,
        0.05009426549077034,
        -0.06817092001438141,
        -0.03456059843301773,
        -0.07364273071289062,
        0.20750921964645386,
        -0.13441678881645203,
        0.031514618545770645,
        -0.0923691838979721,
        -0.160539910197258,
        0.0561349093914032,
        0.019462309777736664,
        0.049629200249910355,
        -0.25334984064102173,
        -0.05476883053779602,
        0.047662943601608276,
        -0.003979858942329884,
        -0.0390876904129982,
        -0.04736020788550377,
        -0.0393383763730526,
        0.0514051616191864,
        0.028981704264879227,
        -0.0009242658270522952,
        0.07177934795618057,
        0.028325039893388748,
        0.02033679187297821,
        -0.06862328201532364,
        -0.096755251288414,
        0.2168344110250473,
        0.02877640910446644,
        0.20388923585414886,
        0.016397729516029358,
        -0.13569265604019165,
        -0.08758863806724548,
        -0.14225272834300995,
        -0.08312955498695374,
        0.08758726716041565,
        -0.044050224125385284,
        -0.06506656110286713,
        0.02724231593310833,
        0.04235215112566948,
        -0.033654216676950455,
        0.06349406391382217,
        -0.1454586386680603,
        -0.06575322896242142,
        0.1858939677476883,
        0.04939429089426994,
        0.20088835060596466,
        0.22503280639648438,
        0.03189269080758095,
        0.10883080959320068,
        0.25775599479675293,
        -0.021631142124533653,
        -0.08597975224256516,
        0.020421287044882774,
        -0.12252142280340195,
        0.11530700325965881,
        0.02143155224621296,
        0.1558096706867218,
        -0.026230089366436005,
        -0.0029041001107543707,
        0.06500989943742752,
        -0.01462226826697588,
        -0.01268913596868515,
        -0.03056555800139904,
        0.049738477915525436,
        -0.13665041327476501,
        0.06042876094579697,
        0.05570822209119797,
        -0.07005776464939117,
        -0.08452686667442322,
        -0.10260000079870224,
        0.019299738109111786,
        -0.1154266968369484,
        0.08355599641799927,
        0.1883595734834671,
        -0.004351562820374966,
        -0.1169949322938919,
        0.12669701874256134,
        -0.12108176946640015,
        0.012573535554111004,
        -0.11859242618083954,
        -0.05357939377427101,
        0.041725825518369675,
        -0.011796812526881695,
        -0.02753467485308647,
        0.19917479157447815,
        -0.16428862512111664,
        0.06205898895859718,
        0.01468665711581707,
        0.14881163835525513,
        -0.03915311396121979,
        0.10601015388965607,
        0.11950739473104477,
        -0.11112933605909348,
        0.0743943303823471,
        -0.09328120946884155,
        0.1788410097360611,
        0.26320764422416687,
        0.17848335206508636,
        -0.059664640575647354,
        -0.10744229704141617,
        0.136952742934227,
        0.08603116124868393,
        -0.02234133519232273,
        -0.05540655553340912,
        -0.3350912034511566,
        0.14763446152210236,
        -0.2056725174188614,
        -0.07474007457494736,
        -0.1678636521100998,
        -0.07799156755208969,
        0.06613265722990036,
        -0.05034395307302475,
        -0.02711609937250614,
        0.0985051840543747,
        -0.08490846306085587,
        -0.043224699795246124,
        -0.06896067410707474,
        -0.10622144490480423,
        -0.04537520557641983,
        -0.037075694650411606,
        -0.10740770399570465,
        0.17267364263534546,
        -0.047725047916173935,
        0.05127306282520294,
        -0.11515939980745316,
        0.19334478676319122,
        0.0510554313659668,
        -0.11989734321832657,
        -0.2083517462015152,
        -0.16097182035446167,
        -0.18726187944412231,
        0.032734017819166183,
        -0.08531267195940018,
        0.012439623475074768,
        -0.10428963601589203,
        -0.16666308045387268,
        0.10781075060367584,
        0.12903761863708496,
        -0.18983089923858643,
        -0.1289377510547638,
        0.06696199625730515,
        0.001351950690150261,
        -0.03296433389186859,
        -0.11934320628643036,
        -0.009428972378373146,
        -0.13992947340011597,
        0.01378574501723051,
        0.054125770926475525,
        0.2405613660812378,
        0.08262503892183304,
        -0.015513647347688675,
        -0.07993811368942261,
        -0.08705808967351913,
        0.24598155915737152,
        -0.15457816421985626,
        -0.11400843411684036,
        0.05172613263130188,
        -0.08705788105726242,
        -0.06103688105940819,
        -0.13378140330314636,
        -0.12000137567520142,
        0.08827344328165054,
        0.0036052244249731302,
        0.030160436406731606,
        0.11631336063146591,
        -0.06353571265935898,
        0.08913671225309372,
        0.08545635640621185,
        0.11372248828411102,
        0.030587049201130867,
        -0.21952377259731293,
        0.0322466678917408,
        -0.023387540131807327,
        0.028393078595399857,
        -0.11273950338363647,
        -0.0033124578185379505,
        0.019413398578763008,
        -0.1078026071190834,
        -0.03944246843457222,
        -0.1203533485531807,
        -0.02556626684963703,
        -0.19107481837272644,
        -0.058420486748218536,
        0.16538847982883453,
        0.11931192129850388,
        0.05878141149878502,
        -0.029957255348563194,
        0.10797112435102463,
        0.007913367822766304,
        -0.0994897112250328,
        0.06160274147987366,
        -0.02202800288796425,
        0.0170791856944561,
        0.002610968193039298,
        0.04809989780187607,
        0.03600392863154411,
        -0.018901804462075233,
        -0.07568439841270447,
        0.17754410207271576,
        0.03547443449497223,
        0.044107213616371155,
        -0.07266822457313538,
        -0.18987055122852325,
        -0.032434966415166855,
        0.03789742663502693,
        0.04723462462425232,
        -0.00041878721094690263,
        -0.17112025618553162,
        -0.01741308718919754,
        -0.0014178454875946045,
        0.17028413712978363,
        -0.0011076475493609905,
        0.009108216501772404,
        0.059048134833574295,
        0.03075750172138214,
        -0.22423072159290314,
        0.029117727652192116,
        -0.014721090905368328,
        -0.029838841408491135,
        -0.03126879036426544,
        -0.10585661232471466,
        0.04326655715703964,
        -0.04351475089788437,
        -0.15017074346542358,
        0.0666903480887413,
        0.13372062146663666,
        0.07375049591064453,
        0.028134793043136597,
        -0.00010296424443367869,
        -0.004648007918149233,
        -0.1432080864906311,
        0.05163703113794327,
        0.030730947852134705,
        -0.04826200380921364,
        0.0790533721446991,
        0.05169219151139259,
        0.07164321094751358,
        0.031207337975502014,
        0.16537557542324066,
        0.10238621383905411,
        -0.08916604518890381,
        0.1319977194070816,
        -0.0750352144241333,
        -0.04144216328859329,
        0.35606953501701355,
        0.13371942937374115,
        -0.15898984670639038,
        0.043738629668951035,
        -0.030540917068719864,
        0.007487427908927202,
        0.10704410821199417,
        0.2136768251657486,
        -0.13134409487247467,
        -0.008428078144788742,
        -0.06197936087846756,
        0.0007798690930940211,
        0.023915816098451614,
        0.021995890885591507,
        0.0674671158194542,
        -0.027787169441580772,
        -0.09682507067918777,
        -0.038062598556280136,
        -0.013279757462441921,
        -0.15481533110141754,
        -0.030487198382616043,
        0.039097800850868225,
        -0.08811015635728836,
        0.11160880327224731,
        0.05510837212204933,
        0.057556211948394775,
        -0.053389742970466614,
        -0.14715000987052917,
        -0.007080093491822481,
        0.026826875284314156,
        -0.08927442878484726,
        -0.014687789604067802,
        -0.02765858918428421,
        0.10379616171121597,
        0.10227533429861069,
        0.07368577271699905,
        0.13714314997196198,
        0.016300641000270844,
        0.02078930474817753,
        0.11003545671701431,
        0.0571526363492012,
        0.046523626893758774,
        0.12023834884166718,
        -0.012526326812803745
      ]
    },
    "cosine": {
      "ueberschrift_vs_fliesstext": 0.595443
    },
    "language_mode": "mixed",
    "zusammenfassung": {
      "modus": "t5",
      "wortanzahl": 71,
      "kurzer_originaltext": "",
      "summary": "die Einführung von KI-Avataren ist mehr als ein Tool-Kauf, weil Prozesse, Systeme und Qualitätskontrollen angepasst werden müssen . Qualitätssicherung verhindert diskriminierende oder falsche Inhalte .",
      "modell": "t5-small"
    },
    "pfade": {
      "json_datei": "data\\processed\\pptx_slide_026.json",
      "assets_verzeichnis": "export\\assets"
    }
  }
}